read_dir/__init__.py
read_dir/read_dir.py
read_dir-1.0.3.dist-info/METADATA
read_dir-1.0.3.dist-info/WHEEL
read_dir-1.0.3.dist-info/top_level.txt
read_dir-1.0.3.dist-info/RECORD
