Metadata-Version: 2.1
Name: read-dir
Version: 1.0.3
Summary: 读取文件
Author: skynyx
Requires-Dist: pandas (>=0.18.0)
Requires-Dist: numpy (>=1.9.2)
